{"dependencies":[{"name":"react","loc":{"line":1,"column":18}},{"name":"react-dom","loc":{"line":2,"column":21}},{"name":"./pages","loc":{"line":3,"column":16}}],"generated":{"js":"\"use strict\";\n\nvar _react = require(\"react\");\n\nvar _react2 = _interopRequireDefault(_react);\n\nvar _reactDom = require(\"react-dom\");\n\nvar _reactDom2 = _interopRequireDefault(_reactDom);\n\nvar _pages = require(\"./pages\");\n\nvar _pages2 = _interopRequireDefault(_pages);\n\nfunction _interopRequireDefault(obj) { return obj && obj.__esModule ? obj : { default: obj }; }\n\n_reactDom2.default.render(_react2.default.createElement(_pages2.default, null), document.querySelector('#app'));\n//# sourceMappingURL=index.js.map"},"hash":"778b2a65d7d1e6d68995735d824478a8"}